bysp/__init__.py
bysp/bysp.py
ByteSplitter-1.0.4.dist-info/METADATA
ByteSplitter-1.0.4.dist-info/WHEEL
ByteSplitter-1.0.4.dist-info/entry_points.txt
ByteSplitter-1.0.4.dist-info/top_level.txt
ByteSplitter-1.0.4.dist-info/RECORD
