Metadata-Version: 2.1
Name: ByteSplitter
Version: 1.0.4
Summary: A tiny Python utility for splitting any binary files into parts and combining them back
Home-page: https://github.com/AivanF/ByteSplitter
Author: AivanF.
Author-email: projects@aivanf.com
License: UNKNOWN
Platform: UNKNOWN
Classifier: Development Status :: 5 - Production/Stable
Classifier: Intended Audience :: Developers
Classifier: Intended Audience :: End Users/Desktop
Classifier: Intended Audience :: Information Technology
Classifier: Programming Language :: Python :: 2
Classifier: Programming Language :: Python :: 3
Classifier: Operating System :: OS Independent
Classifier: Environment :: Console
Classifier: Topic :: Utilities
Classifier: Topic :: Security
Classifier: Topic :: System :: Filesystems
Classifier: License :: Freely Distributable
